bitly_api/__init__.py
bitly_api/bitly_api.py
bitly_api_py3-0.3.dist-info/LICENSE
bitly_api_py3-0.3.dist-info/METADATA
bitly_api_py3-0.3.dist-info/WHEEL
bitly_api_py3-0.3.dist-info/top_level.txt
bitly_api_py3-0.3.dist-info/zip-safe
bitly_api_py3-0.3.dist-info/RECORD
