Metadata-Version: 1.1
Name: bitly_api_py3
Version: 0.3
Summary: An API for bit.ly forked for Python 3 support
Home-page: https://github.com/develtech/bitly-api-python
Author: Jehiah Czebotar
Author-email: jehiah@gmail.com
License: Apache Software License
Keywords: bitly bit.ly
Platform: UNKNOWN
Classifier: Development Status :: 5 - Production/Stable
Classifier: Environment :: Console
Classifier: Intended Audience :: End Users/Desktop
Classifier: Natural Language :: English
Classifier: Operating System :: OS Independent
Classifier: Programming Language :: Python
Classifier: Topic :: Internet :: WWW/HTTP :: Dynamic Content :: CGI Tools/Libraries
Classifier: Topic :: Utilities
Classifier: License :: OSI Approved :: Apache Software License
